qio/__init__.py
qio/versions.py
qio/core/__init__.py
qio/core/quantum_computation_models.py
qio/core/quantum_noise_model.py
qio/core/quantum_program.py
qio/core/quantum_program_result.py
qio/utils/__init__.py
qio/utils/circuit.py
qio/utils/compression.py
qio/utils/qasm.py
qio-0.1.23.dist-info/licenses/LICENSE
qio-0.1.23.dist-info/METADATA
qio-0.1.23.dist-info/WHEEL
qio-0.1.23.dist-info/top_level.txt
qio-0.1.23.dist-info/RECORD
