Metadata-Version: 2.4
Name: qio
Version: 0.1.23
Summary: Common quantum computing objects description and conversion library
License: Apache-2.0
Project-URL: Repository, https://github.com/QuantumCommons/qio
Classifier: Programming Language :: Python :: 3
Classifier: Operating System :: OS Independent
Classifier: Intended Audience :: Developers
Classifier: Intended Audience :: Science/Research
Classifier: Topic :: Scientific/Engineering
Requires-Python: >=3.10
License-File: LICENSE
Requires-Dist: dataclasses
Requires-Dist: dataclasses-json
Dynamic: license-file
